metadata_validator/__init__.py
metadata_validator/contributors.py
metadata_validator/dataset.py
metadata_validator/functions.py
metadata_validator/funders.py
metadata_validator/main.py
metadata_validator/metadata_main.py
metadata_validator/publication.py
metadata_validator/specimen.py
metadata_validator-0.1.6.dist-info/METADATA
metadata_validator-0.1.6.dist-info/WHEEL
metadata_validator-0.1.6.dist-info/top_level.txt
metadata_validator-0.1.6.dist-info/RECORD
