Metadata-Version: 2.1
Name: metadata_validator
Version: 0.1.6
Summary: A package designed to put a spreadsheet of a brain imagery dataset into a series of required metadata validation for within data in cells.
Author-email: Keaton Hutchinson <keatonhutchinson03@gmail.com>
Keywords: python,bil,metadata,validator,metadata validator
Classifier: Development Status :: 3 - Alpha
Classifier: Intended Audience :: Education
Classifier: Programming Language :: Python :: 2
Classifier: Programming Language :: Python :: 3
Classifier: Operating System :: MacOS :: MacOS X
Classifier: Operating System :: Microsoft :: Windows
Requires-Dist: pandas
Requires-Dist: openpyxl
Requires-Dist: requests
Requires-Dist: beautifulsoup4
